any_llm/__init__.py
any_llm/any_llm.py
any_llm/api.py
any_llm/constants.py
any_llm/exceptions.py
any_llm/logging.py
any_llm/py.typed
any_llm/tools.py
any_llm/gateway/__init__.py
any_llm/gateway/alembic.ini
any_llm/gateway/budget.py
any_llm/gateway/cli.py
any_llm/gateway/config.py
any_llm/gateway/log_config.py
any_llm/gateway/pricing_init.py
any_llm/gateway/server.py
any_llm/gateway/alembic/env.py
any_llm/gateway/alembic/script.py.mako
any_llm/gateway/alembic/versions/1e382aa3a9e7_add_per_user_budget_resets.py
any_llm/gateway/alembic/versions/28d153c22616_initial_migration_with_all_models.py
any_llm/gateway/alembic/versions/e7c85cc73bfa_convert_budget_duration_to_seconds.py
any_llm/gateway/auth/__init__.py
any_llm/gateway/auth/dependencies.py
any_llm/gateway/auth/models.py
any_llm/gateway/auth/vertex_auth.py
any_llm/gateway/db/__init__.py
any_llm/gateway/db/models.py
any_llm/gateway/db/session.py
any_llm/gateway/routes/__init__.py
any_llm/gateway/routes/budgets.py
any_llm/gateway/routes/chat.py
any_llm/gateway/routes/health.py
any_llm/gateway/routes/keys.py
any_llm/gateway/routes/pricing.py
any_llm/gateway/routes/users.py
any_llm/providers/__init__.py
any_llm/providers/anthropic/__init__.py
any_llm/providers/anthropic/anthropic.py
any_llm/providers/anthropic/utils.py
any_llm/providers/azure/__init__.py
any_llm/providers/azure/azure.py
any_llm/providers/azure/utils.py
any_llm/providers/azureopenai/__init__.py
any_llm/providers/azureopenai/azureopenai.py
any_llm/providers/bedrock/__init__.py
any_llm/providers/bedrock/bedrock.py
any_llm/providers/bedrock/utils.py
any_llm/providers/cerebras/__init__.py
any_llm/providers/cerebras/cerebras.py
any_llm/providers/cerebras/utils.py
any_llm/providers/cohere/__init__.py
any_llm/providers/cohere/cohere.py
any_llm/providers/cohere/utils.py
any_llm/providers/databricks/__init__.py
any_llm/providers/databricks/databricks.py
any_llm/providers/deepseek/__init__.py
any_llm/providers/deepseek/deepseek.py
any_llm_sdk-1.7.0.dist-info/licenses/LICENSE
any_llm_sdk-1.7.0.dist-info/METADATA
any_llm_sdk-1.7.0.dist-info/WHEEL
any_llm_sdk-1.7.0.dist-info/entry_points.txt
any_llm_sdk-1.7.0.dist-info/top_level.txt
any_llm_sdk-1.7.0.dist-info/RECORD
