Metadata-Version: 2.4
Name: any-llm-sdk
Version: 1.7.0
License: Apache-2.0
Project-URL: Documentation, https://mozilla-ai.github.io/any-llm/
Project-URL: Issues, https://github.com/mozilla-ai/any-llm/issues
Project-URL: Source, https://github.com/mozilla-ai/any-llm
Requires-Python: >=3.11
License-File: LICENSE
Requires-Dist: pydantic<3,>2
Requires-Dist: openai>=1.99.3
Requires-Dist: rich
Requires-Dist: httpx
Provides-Extra: all
Requires-Dist: any-llm-sdk[anthropic,azure,azureopenai,bedrock,cerebras,cohere,databricks,deepseek,fireworks,gateway,gemini,groq,huggingface,inception,llama,llamacpp,llamafile,lmstudio,minimax,mistral,moonshot,nebius,ollama,openai,openrouter,perplexity,platform,portkey,sagemaker,sambanova,together,vertexai,vllm,voyage,watsonx,xai,zai]; extra == "all"
Provides-Extra: platform
Requires-Dist: any-llm-platform-client>=0.2.0; extra == "platform"
Provides-Extra: perplexity
Provides-Extra: mistral
Requires-Dist: mistralai>=1.9.3; extra == "mistral"
Provides-Extra: anthropic
Requires-Dist: anthropic; extra == "anthropic"
Provides-Extra: gemini
Requires-Dist: google-genai; extra == "gemini"
Provides-Extra: vertexai
Requires-Dist: google-genai; extra == "vertexai"
Provides-Extra: huggingface
Requires-Dist: huggingface-hub; extra == "huggingface"
Provides-Extra: cohere
Requires-Dist: cohere; extra == "cohere"
Provides-Extra: cerebras
Requires-Dist: cerebras_cloud_sdk>=1.23.0; extra == "cerebras"
Provides-Extra: groq
Requires-Dist: groq; extra == "groq"
Provides-Extra: bedrock
Requires-Dist: boto3; extra == "bedrock"
Provides-Extra: azure
Requires-Dist: azure-ai-inference; extra == "azure"
Provides-Extra: watsonx
Requires-Dist: ibm-watsonx-ai; extra == "watsonx"
Provides-Extra: together
Requires-Dist: together>=1.5.34; extra == "together"
Provides-Extra: ollama
Requires-Dist: ollama>=0.5.1; extra == "ollama"
Provides-Extra: voyage
Requires-Dist: voyageai; extra == "voyage"
Provides-Extra: xai
Requires-Dist: xai-sdk>=1.0.1; extra == "xai"
Provides-Extra: sagemaker
Requires-Dist: boto3; extra == "sagemaker"
Provides-Extra: azureopenai
Provides-Extra: databricks
Provides-Extra: deepseek
Provides-Extra: fireworks
Provides-Extra: inception
Provides-Extra: llama
Provides-Extra: llamacpp
Provides-Extra: llamafile
Provides-Extra: lmstudio
Provides-Extra: moonshot
Provides-Extra: nebius
Provides-Extra: openai
Provides-Extra: openrouter
Provides-Extra: portkey
Provides-Extra: sambanova
Provides-Extra: minimax
Provides-Extra: vllm
Provides-Extra: gateway
Requires-Dist: fastapi>=0.115.0; extra == "gateway"
Requires-Dist: uvicorn[standard]>=0.30.0; extra == "gateway"
Requires-Dist: sqlalchemy>=2.0.0; extra == "gateway"
Requires-Dist: alembic>=1.13.0; extra == "gateway"
Requires-Dist: pydantic-settings>=2.0.0; extra == "gateway"
Requires-Dist: pyyaml>=6.0; extra == "gateway"
Requires-Dist: click>=8.1.0; extra == "gateway"
Requires-Dist: python-dotenv>=1.0.0; extra == "gateway"
Requires-Dist: psycopg2-binary>=2.9.9; extra == "gateway"
Provides-Extra: zai
Dynamic: license-file
